yamlgenerator_hook_search/__init__.py
yamlgenerator_hook_search-1.0.2.dist-info/METADATA
yamlgenerator_hook_search-1.0.2.dist-info/WHEEL
yamlgenerator_hook_search-1.0.2.dist-info/RECORD
